{
  "meta": {
    "lastRun": "2026-06-27T10:05:55.326Z",
    "sourcesMonitored": 14
  },
  "sources": [
    {
      "key": "UNECE_WP29_GRVA",
      "name": "UNECE WP.29 GRVA — Automated Driving",
      "authority": "UNECE WP.29 GRVA",
      "region": "Autonomous Vehicles",
      "url": "https://unece.org/transport/vehicle-regulations-wp29/working-parties/grva",
      "lastChecked": "2026-06-27T10:05:32.677Z",
      "status": "unchanged",
      "chars": 487,
      "delta": 0
    },
    {
      "key": "NHTSA_AV",
      "name": "NHTSA — Automated Vehicles Safety",
      "authority": "NHTSA",
      "region": "Autonomous Vehicles",
      "url": "https://www.nhtsa.gov/vehicle-safety/automated-vehicles-safety",
      "lastChecked": "2026-06-27T10:05:36.632Z",
      "status": "unchanged",
      "chars": 10928,
      "delta": 0
    },
    {
      "key": "NHTSA_SGO",
      "name": "NHTSA — Standing General Order (AV Crash Reporting)",
      "authority": "NHTSA",
      "region": "Autonomous Vehicles",
      "url": "https://www.nhtsa.gov/laws-regulations/standing-general-order-crash-reporting",
      "lastChecked": "2026-06-27T10:05:38.154Z",
      "status": "changed",
      "chars": 18915,
      "delta": 47
    },
    {
      "key": "CA_DMV_AV",
      "name": "California DMV — Autonomous Vehicles",
      "authority": "California DMV",
      "region": "Autonomous Vehicles",
      "url": "https://www.dmv.ca.gov/portal/vehicle-industry-services/autonomous-vehicles/",
      "lastChecked": "2026-06-27T10:05:39.610Z",
      "status": "changed",
      "chars": 21801,
      "delta": -47
    },
    {
      "key": "CA_CPUC_AV",
      "name": "California CPUC — Autonomous Vehicle Programs",
      "authority": "California CPUC",
      "region": "Autonomous Vehicles",
      "url": "https://www.cpuc.ca.gov/regulatory-services/licensing/transportation-licensing-and-analysis-branch/autonomous-vehicle-programs",
      "lastChecked": "2026-06-27T10:05:41.063Z",
      "status": "unchanged",
      "chars": 8414,
      "delta": 0
    },
    {
      "key": "ISO_TC299",
      "name": "ISO/TC 299 Robotics (ISO 10218, 15066, 13482)",
      "authority": "ISO/TC 299",
      "region": "Robotics & Machinery Safety",
      "url": "https://www.iso.org/committee/5915511.html",
      "lastChecked": "2026-06-27T10:05:42.560Z",
      "status": "changed",
      "chars": 25463,
      "delta": 89
    },
    {
      "key": "A3_RIA",
      "name": "A3 / RIA — Robot Safety Standards (R15.06)",
      "authority": "A3 / RIA",
      "region": "Robotics & Machinery Safety",
      "url": "https://www.automate.org/robotics/standards",
      "lastChecked": "2026-06-27T10:05:44.125Z",
      "status": "changed",
      "chars": 26247,
      "delta": 3250
    },
    {
      "key": "OSHA_ROBOTICS",
      "name": "OSHA — Robotics",
      "authority": "OSHA",
      "region": "Robotics & Machinery Safety",
      "url": "https://www.osha.gov/robotics",
      "lastChecked": "2026-06-27T10:05:45.625Z",
      "status": "changed",
      "chars": 17560,
      "delta": 0
    },
    {
      "key": "EU_MACHINERY",
      "name": "EU Machinery Regulation 2023/1230",
      "authority": "European Commission",
      "region": "Robotics & Machinery Safety",
      "url": "https://single-market-economy.ec.europa.eu/sectors/mechanical-engineering/machinery_en",
      "lastChecked": "2026-06-27T10:05:47.079Z",
      "status": "unchanged",
      "chars": 9357,
      "delta": 0
    },
    {
      "key": "ISO_TC22",
      "name": "ISO/TC 22 Road Vehicles (ISO 26262, 21448 SOTIF, 22737)",
      "authority": "ISO/TC 22",
      "region": "Functional Safety",
      "url": "https://www.iso.org/committee/46706.html",
      "lastChecked": "2026-06-27T10:05:48.712Z",
      "status": "changed",
      "chars": 28233,
      "delta": 0
    },
    {
      "key": "IEC_61508",
      "name": "IEC — Functional Safety (IEC 61508)",
      "authority": "IEC",
      "region": "Functional Safety",
      "url": "https://www.iec.ch/functionalsafety",
      "lastChecked": "2026-06-27T10:05:50.189Z",
      "status": "changed",
      "chars": 28183,
      "delta": 0
    },
    {
      "key": "EU_AI_ACT",
      "name": "EU AI Act — Regulatory Framework",
      "authority": "European Commission",
      "region": "AI Governance",
      "url": "https://digital-strategy.ec.europa.eu/en/policies/regulatory-framework-ai",
      "lastChecked": "2026-06-27T10:05:51.895Z",
      "status": "changed",
      "chars": 12416,
      "delta": -18334
    },
    {
      "key": "NIST_AI_RMF",
      "name": "NIST — AI Risk Management Framework",
      "authority": "NIST",
      "region": "AI Governance",
      "url": "https://www.nist.gov/itl/ai-risk-management-framework",
      "lastChecked": "2026-06-27T10:05:53.504Z",
      "status": "unchanged",
      "chars": 6163,
      "delta": 0
    },
    {
      "key": "FAA_UAS",
      "name": "FAA — UAS / Drones",
      "authority": "FAA",
      "region": "Drones / UAS",
      "url": "https://www.faa.gov/uas",
      "lastChecked": "2026-06-27T10:05:54.880Z",
      "status": "changed",
      "chars": 19519,
      "delta": 0
    }
  ],
  "changes": [
    {
      "date": "2026-06-27T10:05:38.154Z",
      "region": "Autonomous Vehicles",
      "authority": "NHTSA",
      "url": "https://www.nhtsa.gov/laws-regulations/standing-general-order-crash-reporting",
      "note": "Change detected (Δ +47 chars)"
    },
    {
      "date": "2026-06-27T10:05:39.610Z",
      "region": "Autonomous Vehicles",
      "authority": "California DMV",
      "url": "https://www.dmv.ca.gov/portal/vehicle-industry-services/autonomous-vehicles/",
      "note": "Change detected (Δ -47 chars)"
    },
    {
      "date": "2026-06-27T10:05:42.560Z",
      "region": "Robotics & Machinery Safety",
      "authority": "ISO/TC 299",
      "url": "https://www.iso.org/committee/5915511.html",
      "note": "Change detected (Δ +89 chars)"
    },
    {
      "date": "2026-06-27T10:05:44.125Z",
      "region": "Robotics & Machinery Safety",
      "authority": "A3 / RIA",
      "url": "https://www.automate.org/robotics/standards",
      "note": "Change detected (Δ +3250 chars)"
    },
    {
      "date": "2026-06-27T10:05:45.625Z",
      "region": "Robotics & Machinery Safety",
      "authority": "OSHA",
      "url": "https://www.osha.gov/robotics",
      "note": "Change detected (Δ +0 chars)"
    },
    {
      "date": "2026-06-27T10:05:48.712Z",
      "region": "Functional Safety",
      "authority": "ISO/TC 22",
      "url": "https://www.iso.org/committee/46706.html",
      "note": "Change detected (Δ +0 chars)"
    },
    {
      "date": "2026-06-27T10:05:50.189Z",
      "region": "Functional Safety",
      "authority": "IEC",
      "url": "https://www.iec.ch/functionalsafety",
      "note": "Change detected (Δ +0 chars)"
    },
    {
      "date": "2026-06-27T10:05:51.895Z",
      "region": "AI Governance",
      "authority": "European Commission",
      "url": "https://digital-strategy.ec.europa.eu/en/policies/regulatory-framework-ai",
      "note": "Change detected (Δ -18334 chars)"
    },
    {
      "date": "2026-06-27T10:05:54.880Z",
      "region": "Drones / UAS",
      "authority": "FAA",
      "url": "https://www.faa.gov/uas",
      "note": "Change detected (Δ +0 chars)"
    },
    {
      "date": "2026-06-26T10:48:59.577Z",
      "region": "Autonomous Vehicles",
      "authority": "NHTSA",
      "url": "https://www.nhtsa.gov/laws-regulations/standing-general-order-crash-reporting",
      "note": "Change detected (Δ -47 chars)"
    },
    {
      "date": "2026-06-26T10:49:01.074Z",
      "region": "Autonomous Vehicles",
      "authority": "California DMV",
      "url": "https://www.dmv.ca.gov/portal/vehicle-industry-services/autonomous-vehicles/",
      "note": "Change detected (Δ +0 chars)"
    },
    {
      "date": "2026-06-26T10:49:04.227Z",
      "region": "Robotics & Machinery Safety",
      "authority": "ISO/TC 299",
      "url": "https://www.iso.org/committee/5915511.html",
      "note": "Change detected (Δ -79 chars)"
    },
    {
      "date": "2026-06-26T10:49:05.681Z",
      "region": "Robotics & Machinery Safety",
      "authority": "A3 / RIA",
      "url": "https://www.automate.org/robotics/standards",
      "note": "Change detected (Δ -120 chars)"
    },
    {
      "date": "2026-06-26T10:49:07.171Z",
      "region": "Robotics & Machinery Safety",
      "authority": "OSHA",
      "url": "https://www.osha.gov/robotics",
      "note": "Change detected (Δ +0 chars)"
    },
    {
      "date": "2026-06-26T10:49:10.377Z",
      "region": "Functional Safety",
      "authority": "ISO/TC 22",
      "url": "https://www.iso.org/committee/46706.html",
      "note": "Change detected (Δ -135 chars)"
    },
    {
      "date": "2026-06-26T10:49:11.870Z",
      "region": "Functional Safety",
      "authority": "IEC",
      "url": "https://www.iec.ch/functionalsafety",
      "note": "Change detected (Δ +0 chars)"
    },
    {
      "date": "2026-06-26T10:49:13.429Z",
      "region": "AI Governance",
      "authority": "European Commission",
      "url": "https://digital-strategy.ec.europa.eu/en/policies/regulatory-framework-ai",
      "note": "Change detected (Δ +47 chars)"
    },
    {
      "date": "2026-06-26T10:49:16.649Z",
      "region": "Drones / UAS",
      "authority": "FAA",
      "url": "https://www.faa.gov/uas",
      "note": "Change detected (Δ +0 chars)"
    },
    {
      "date": "2026-06-25T10:39:35.877Z",
      "region": "Autonomous Vehicles",
      "authority": "NHTSA",
      "url": "https://www.nhtsa.gov/laws-regulations/standing-general-order-crash-reporting",
      "note": "Change detected (Δ +0 chars)"
    },
    {
      "date": "2026-06-25T10:39:37.396Z",
      "region": "Autonomous Vehicles",
      "authority": "California DMV",
      "url": "https://www.dmv.ca.gov/portal/vehicle-industry-services/autonomous-vehicles/",
      "note": "Change detected (Δ +0 chars)"
    },
    {
      "date": "2026-06-25T10:39:40.322Z",
      "region": "Robotics & Machinery Safety",
      "authority": "ISO/TC 299",
      "url": "https://www.iso.org/committee/5915511.html",
      "note": "Change detected (Δ +79 chars)"
    },
    {
      "date": "2026-06-25T10:39:41.822Z",
      "region": "Robotics & Machinery Safety",
      "authority": "A3 / RIA",
      "url": "https://www.automate.org/robotics/standards",
      "note": "Change detected (Δ -3144 chars)"
    },
    {
      "date": "2026-06-25T10:39:43.326Z",
      "region": "Robotics & Machinery Safety",
      "authority": "OSHA",
      "url": "https://www.osha.gov/robotics",
      "note": "Change detected (Δ -4 chars)"
    },
    {
      "date": "2026-06-25T10:39:46.319Z",
      "region": "Functional Safety",
      "authority": "ISO/TC 22",
      "url": "https://www.iso.org/committee/46706.html",
      "note": "Change detected (Δ -3833 chars)"
    },
    {
      "date": "2026-06-25T10:39:47.774Z",
      "region": "Functional Safety",
      "authority": "IEC",
      "url": "https://www.iec.ch/functionalsafety",
      "note": "Change detected (Δ +0 chars)"
    },
    {
      "date": "2026-06-25T10:39:49.210Z",
      "region": "AI Governance",
      "authority": "European Commission",
      "url": "https://digital-strategy.ec.europa.eu/en/policies/regulatory-framework-ai",
      "note": "Change detected (Δ -47 chars)"
    },
    {
      "date": "2026-06-25T10:39:55.283Z",
      "region": "AI Governance",
      "authority": "NIST",
      "url": "https://www.nist.gov/itl/ai-risk-management-framework",
      "note": "Change detected (Δ -696 chars)"
    },
    {
      "date": "2026-06-25T10:39:56.711Z",
      "region": "Drones / UAS",
      "authority": "FAA",
      "url": "https://www.faa.gov/uas",
      "note": "Change detected (Δ +0 chars)"
    },
    {
      "date": "2026-06-24T10:46:37.342Z",
      "region": "Autonomous Vehicles",
      "authority": "NHTSA",
      "url": "https://www.nhtsa.gov/vehicle-safety/automated-vehicles-safety",
      "note": "Change detected (Δ +0 chars)"
    },
    {
      "date": "2026-06-24T10:46:38.741Z",
      "region": "Autonomous Vehicles",
      "authority": "NHTSA",
      "url": "https://www.nhtsa.gov/laws-regulations/standing-general-order-crash-reporting",
      "note": "Change detected (Δ +0 chars)"
    },
    {
      "date": "2026-06-24T10:46:40.179Z",
      "region": "Autonomous Vehicles",
      "authority": "California DMV",
      "url": "https://www.dmv.ca.gov/portal/vehicle-industry-services/autonomous-vehicles/",
      "note": "Change detected (Δ +47 chars)"
    },
    {
      "date": "2026-06-24T10:46:43.076Z",
      "region": "Robotics & Machinery Safety",
      "authority": "ISO/TC 299",
      "url": "https://www.iso.org/committee/5915511.html",
      "note": "Change detected (Δ +0 chars)"
    },
    {
      "date": "2026-06-24T10:46:44.544Z",
      "region": "Robotics & Machinery Safety",
      "authority": "A3 / RIA",
      "url": "https://www.automate.org/robotics/standards",
      "note": "Change detected (Δ -2 chars)"
    },
    {
      "date": "2026-06-24T10:46:46.106Z",
      "region": "Robotics & Machinery Safety",
      "authority": "OSHA",
      "url": "https://www.osha.gov/robotics",
      "note": "Change detected (Δ +345 chars)"
    },
    {
      "date": "2026-06-24T10:46:49.129Z",
      "region": "Functional Safety",
      "authority": "ISO/TC 22",
      "url": "https://www.iso.org/committee/46706.html",
      "note": "Change detected (Δ +3736 chars)"
    },
    {
      "date": "2026-06-24T10:46:50.521Z",
      "region": "Functional Safety",
      "authority": "IEC",
      "url": "https://www.iec.ch/functionalsafety",
      "note": "Change detected (Δ +0 chars)"
    },
    {
      "date": "2026-06-24T10:46:51.996Z",
      "region": "AI Governance",
      "authority": "European Commission",
      "url": "https://digital-strategy.ec.europa.eu/en/policies/regulatory-framework-ai",
      "note": "Change detected (Δ +18334 chars)"
    },
    {
      "date": "2026-06-24T10:46:53.578Z",
      "region": "AI Governance",
      "authority": "NIST",
      "url": "https://www.nist.gov/itl/ai-risk-management-framework",
      "note": "Change detected (Δ +696 chars)"
    },
    {
      "date": "2026-06-24T10:46:54.935Z",
      "region": "Drones / UAS",
      "authority": "FAA",
      "url": "https://www.faa.gov/uas",
      "note": "Change detected (Δ +0 chars)"
    },
    {
      "date": "2026-06-23T11:14:01.790Z",
      "region": "Autonomous Vehicles",
      "authority": "NHTSA",
      "url": "https://www.nhtsa.gov/vehicle-safety/automated-vehicles-safety",
      "note": "Change detected (Δ +0 chars)"
    },
    {
      "date": "2026-06-23T11:14:03.234Z",
      "region": "Autonomous Vehicles",
      "authority": "NHTSA",
      "url": "https://www.nhtsa.gov/laws-regulations/standing-general-order-crash-reporting",
      "note": "Change detected (Δ +0 chars)"
    },
    {
      "date": "2026-06-23T11:14:07.605Z",
      "region": "Robotics & Machinery Safety",
      "authority": "ISO/TC 299",
      "url": "https://www.iso.org/committee/5915511.html",
      "note": "Change detected (Δ +61 chars)"
    },
    {
      "date": "2026-06-23T11:14:09.156Z",
      "region": "Robotics & Machinery Safety",
      "authority": "A3 / RIA",
      "url": "https://www.automate.org/robotics/standards",
      "note": "Change detected (Δ -70 chars)"
    },
    {
      "date": "2026-06-23T11:14:10.654Z",
      "region": "Robotics & Machinery Safety",
      "authority": "OSHA",
      "url": "https://www.osha.gov/robotics",
      "note": "Change detected (Δ +0 chars)"
    },
    {
      "date": "2026-06-23T11:14:13.752Z",
      "region": "Functional Safety",
      "authority": "ISO/TC 22",
      "url": "https://www.iso.org/committee/46706.html",
      "note": "Change detected (Δ +0 chars)"
    },
    {
      "date": "2026-06-23T11:14:18.156Z",
      "region": "AI Governance",
      "authority": "European Commission",
      "url": "https://digital-strategy.ec.europa.eu/en/policies/regulatory-framework-ai",
      "note": "Change detected (Δ -18334 chars)"
    },
    {
      "date": "2026-06-23T11:14:21.193Z",
      "region": "Drones / UAS",
      "authority": "FAA",
      "url": "https://www.faa.gov/uas",
      "note": "Change detected (Δ +0 chars)"
    },
    {
      "date": "2026-06-22T13:33:08.116Z",
      "region": "Autonomous Vehicles",
      "authority": "NHTSA",
      "url": "https://www.nhtsa.gov/laws-regulations/standing-general-order-crash-reporting",
      "note": "Change detected (Δ +0 chars)"
    },
    {
      "date": "2026-06-22T13:33:09.648Z",
      "region": "Autonomous Vehicles",
      "authority": "California DMV",
      "url": "https://www.dmv.ca.gov/portal/vehicle-industry-services/autonomous-vehicles/",
      "note": "Change detected (Δ -39 chars)"
    },
    {
      "date": "2026-06-22T13:33:13.705Z",
      "region": "Robotics & Machinery Safety",
      "authority": "ISO/TC 299",
      "url": "https://www.iso.org/committee/5915511.html",
      "note": "Change detected (Δ +21 chars)"
    },
    {
      "date": "2026-06-22T13:33:15.250Z",
      "region": "Robotics & Machinery Safety",
      "authority": "A3 / RIA",
      "url": "https://www.automate.org/robotics/standards",
      "note": "Change detected (Δ -23 chars)"
    },
    {
      "date": "2026-06-22T13:33:16.699Z",
      "region": "Robotics & Machinery Safety",
      "authority": "OSHA",
      "url": "https://www.osha.gov/robotics",
      "note": "Change detected (Δ -415 chars)"
    },
    {
      "date": "2026-06-22T13:33:19.741Z",
      "region": "Functional Safety",
      "authority": "ISO/TC 22",
      "url": "https://www.iso.org/committee/46706.html",
      "note": "Change detected (Δ +139 chars)"
    },
    {
      "date": "2026-06-22T13:33:21.321Z",
      "region": "Functional Safety",
      "authority": "IEC",
      "url": "https://www.iec.ch/functionalsafety",
      "note": "Change detected (Δ -31 chars)"
    },
    {
      "date": "2026-06-22T13:33:22.805Z",
      "region": "AI Governance",
      "authority": "European Commission",
      "url": "https://digital-strategy.ec.europa.eu/en/policies/regulatory-framework-ai",
      "note": "Change detected (Δ +18334 chars)"
    },
    {
      "date": "2026-06-22T13:33:24.460Z",
      "region": "AI Governance",
      "authority": "NIST",
      "url": "https://www.nist.gov/itl/ai-risk-management-framework",
      "note": "Change detected (Δ -696 chars)"
    },
    {
      "date": "2026-06-22T13:33:25.959Z",
      "region": "Drones / UAS",
      "authority": "FAA",
      "url": "https://www.faa.gov/uas",
      "note": "Change detected (Δ +0 chars)"
    },
    {
      "date": "2026-06-21T11:13:57.631Z",
      "region": "Autonomous Vehicles",
      "authority": "NHTSA",
      "url": "https://www.nhtsa.gov/vehicle-safety/automated-vehicles-safety",
      "note": "Change detected (Δ +0 chars)"
    },
    {
      "date": "2026-06-21T11:13:59.144Z",
      "region": "Autonomous Vehicles",
      "authority": "NHTSA",
      "url": "https://www.nhtsa.gov/laws-regulations/standing-general-order-crash-reporting",
      "note": "Change detected (Δ +0 chars)"
    },
    {
      "date": "2026-06-21T11:14:00.572Z",
      "region": "Autonomous Vehicles",
      "authority": "California DMV",
      "url": "https://www.dmv.ca.gov/portal/vehicle-industry-services/autonomous-vehicles/",
      "note": "Change detected (Δ -47 chars)"
    },
    {
      "date": "2026-06-21T11:14:03.808Z",
      "region": "Robotics & Machinery Safety",
      "authority": "ISO/TC 299",
      "url": "https://www.iso.org/committee/5915511.html",
      "note": "Change detected (Δ +0 chars)"
    },
    {
      "date": "2026-06-21T11:14:05.254Z",
      "region": "Robotics & Machinery Safety",
      "authority": "A3 / RIA",
      "url": "https://www.automate.org/robotics/standards",
      "note": "Change detected (Δ -988 chars)"
    },
    {
      "date": "2026-06-21T11:14:07.512Z",
      "region": "Robotics & Machinery Safety",
      "authority": "OSHA",
      "url": "https://www.osha.gov/robotics",
      "note": "Change detected (Δ +0 chars)"
    },
    {
      "date": "2026-06-21T11:14:10.653Z",
      "region": "Functional Safety",
      "authority": "ISO/TC 22",
      "url": "https://www.iso.org/committee/46706.html",
      "note": "Change detected (Δ -61 chars)"
    },
    {
      "date": "2026-06-21T11:14:12.251Z",
      "region": "Functional Safety",
      "authority": "IEC",
      "url": "https://www.iec.ch/functionalsafety",
      "note": "Change detected (Δ +0 chars)"
    },
    {
      "date": "2026-06-21T11:14:13.859Z",
      "region": "AI Governance",
      "authority": "European Commission",
      "url": "https://digital-strategy.ec.europa.eu/en/policies/regulatory-framework-ai",
      "note": "Change detected (Δ -18374 chars)"
    },
    {
      "date": "2026-06-21T11:14:15.523Z",
      "region": "AI Governance",
      "authority": "NIST",
      "url": "https://www.nist.gov/itl/ai-risk-management-framework",
      "note": "Change detected (Δ +696 chars)"
    },
    {
      "date": "2026-06-21T11:14:16.937Z",
      "region": "Drones / UAS",
      "authority": "FAA",
      "url": "https://www.faa.gov/uas",
      "note": "Change detected (Δ +0 chars)"
    },
    {
      "date": "2026-06-20T10:31:01.809Z",
      "region": "Autonomous Vehicles",
      "authority": "NHTSA",
      "url": "https://www.nhtsa.gov/vehicle-safety/automated-vehicles-safety",
      "note": "Change detected (Δ +0 chars)"
    },
    {
      "date": "2026-06-20T10:31:03.318Z",
      "region": "Autonomous Vehicles",
      "authority": "NHTSA",
      "url": "https://www.nhtsa.gov/laws-regulations/standing-general-order-crash-reporting",
      "note": "Change detected (Δ +0 chars)"
    },
    {
      "date": "2026-06-20T10:31:04.988Z",
      "region": "Autonomous Vehicles",
      "authority": "California DMV",
      "url": "https://www.dmv.ca.gov/portal/vehicle-industry-services/autonomous-vehicles/",
      "note": "Change detected (Δ +47 chars)"
    },
    {
      "date": "2026-06-20T10:31:08.233Z",
      "region": "Robotics & Machinery Safety",
      "authority": "ISO/TC 299",
      "url": "https://www.iso.org/committee/5915511.html",
      "note": "Change detected (Δ +0 chars)"
    },
    {
      "date": "2026-06-20T10:31:09.874Z",
      "region": "Robotics & Machinery Safety",
      "authority": "A3 / RIA",
      "url": "https://www.automate.org/robotics/standards",
      "note": "Change detected (Δ +987 chars)"
    },
    {
      "date": "2026-06-20T10:31:11.407Z",
      "region": "Robotics & Machinery Safety",
      "authority": "OSHA",
      "url": "https://www.osha.gov/robotics",
      "note": "Change detected (Δ +345 chars)"
    },
    {
      "date": "2026-06-20T10:31:14.463Z",
      "region": "Functional Safety",
      "authority": "ISO/TC 22",
      "url": "https://www.iso.org/committee/46706.html",
      "note": "Change detected (Δ +0 chars)"
    },
    {
      "date": "2026-06-20T10:31:16.011Z",
      "region": "Functional Safety",
      "authority": "IEC",
      "url": "https://www.iec.ch/functionalsafety",
      "note": "Change detected (Δ +0 chars)"
    },
    {
      "date": "2026-06-20T10:31:17.596Z",
      "region": "AI Governance",
      "authority": "European Commission",
      "url": "https://digital-strategy.ec.europa.eu/en/policies/regulatory-framework-ai",
      "note": "Change detected (Δ +0 chars)"
    },
    {
      "date": "2026-06-20T10:31:19.157Z",
      "region": "AI Governance",
      "authority": "NIST",
      "url": "https://www.nist.gov/itl/ai-risk-management-framework",
      "note": "Change detected (Δ -696 chars)"
    },
    {
      "date": "2026-06-20T10:31:20.546Z",
      "region": "Drones / UAS",
      "authority": "FAA",
      "url": "https://www.faa.gov/uas",
      "note": "Change detected (Δ +0 chars)"
    },
    {
      "date": "2026-06-19T12:04:08.408Z",
      "region": "Autonomous Vehicles",
      "authority": "UNECE WP.29 GRVA",
      "url": "https://unece.org/transport/vehicle-regulations-wp29/working-parties/grva",
      "note": "Change detected (Δ -50 chars)"
    },
    {
      "date": "2026-06-19T12:04:14.207Z",
      "region": "Autonomous Vehicles",
      "authority": "NHTSA",
      "url": "https://www.nhtsa.gov/vehicle-safety/automated-vehicles-safety",
      "note": "Change detected (Δ +47 chars)"
    },
    {
      "date": "2026-06-19T12:04:15.654Z",
      "region": "Autonomous Vehicles",
      "authority": "NHTSA",
      "url": "https://www.nhtsa.gov/laws-regulations/standing-general-order-crash-reporting",
      "note": "Change detected (Δ +0 chars)"
    },
    {
      "date": "2026-06-19T12:04:17.117Z",
      "region": "Autonomous Vehicles",
      "authority": "California DMV",
      "url": "https://www.dmv.ca.gov/portal/vehicle-industry-services/autonomous-vehicles/",
      "note": "Change detected (Δ -47 chars)"
    },
    {
      "date": "2026-06-19T12:04:23.528Z",
      "region": "Robotics & Machinery Safety",
      "authority": "ISO/TC 299",
      "url": "https://www.iso.org/committee/5915511.html",
      "note": "Change detected (Δ +88 chars)"
    },
    {
      "date": "2026-06-19T12:04:25.095Z",
      "region": "Robotics & Machinery Safety",
      "authority": "A3 / RIA",
      "url": "https://www.automate.org/robotics/standards",
      "note": "Change detected (Δ +0 chars)"
    },
    {
      "date": "2026-06-19T12:04:26.579Z",
      "region": "Robotics & Machinery Safety",
      "authority": "OSHA",
      "url": "https://www.osha.gov/robotics",
      "note": "Change detected (Δ +4 chars)"
    },
    {
      "date": "2026-06-19T12:04:29.845Z",
      "region": "Functional Safety",
      "authority": "ISO/TC 22",
      "url": "https://www.iso.org/committee/46706.html",
      "note": "Change detected (Δ +88 chars)"
    },
    {
      "date": "2026-06-19T12:04:31.312Z",
      "region": "Functional Safety",
      "authority": "IEC",
      "url": "https://www.iec.ch/functionalsafety",
      "note": "Change detected (Δ +197 chars)"
    },
    {
      "date": "2026-06-19T12:04:32.914Z",
      "region": "AI Governance",
      "authority": "European Commission",
      "url": "https://digital-strategy.ec.europa.eu/en/policies/regulatory-framework-ai",
      "note": "Change detected (Δ +18374 chars)"
    },
    {
      "date": "2026-06-19T12:04:34.504Z",
      "region": "AI Governance",
      "authority": "NIST",
      "url": "https://www.nist.gov/itl/ai-risk-management-framework",
      "note": "Change detected (Δ +696 chars)"
    },
    {
      "date": "2026-06-19T12:04:35.888Z",
      "region": "Drones / UAS",
      "authority": "FAA",
      "url": "https://www.faa.gov/uas",
      "note": "Change detected (Δ +0 chars)"
    },
    {
      "date": "2026-06-18T11:52:15.776Z",
      "region": "Autonomous Vehicles",
      "authority": "NHTSA",
      "url": "https://www.nhtsa.gov/vehicle-safety/automated-vehicles-safety",
      "note": "Change detected (Δ -47 chars)"
    },
    {
      "date": "2026-06-18T11:52:19.698Z",
      "region": "Autonomous Vehicles",
      "authority": "NHTSA",
      "url": "https://www.nhtsa.gov/laws-regulations/standing-general-order-crash-reporting",
      "note": "Change detected (Δ +0 chars)"
    },
    {
      "date": "2026-06-18T11:52:21.081Z",
      "region": "Autonomous Vehicles",
      "authority": "California DMV",
      "url": "https://www.dmv.ca.gov/portal/vehicle-industry-services/autonomous-vehicles/",
      "note": "Change detected (Δ +0 chars)"
    },
    {
      "date": "2026-06-18T11:52:27.449Z",
      "region": "Robotics & Machinery Safety",
      "authority": "ISO/TC 299",
      "url": "https://www.iso.org/committee/5915511.html",
      "note": "Change detected (Δ +0 chars)"
    },
    {
      "date": "2026-06-18T11:52:28.882Z",
      "region": "Robotics & Machinery Safety",
      "authority": "A3 / RIA",
      "url": "https://www.automate.org/robotics/standards",
      "note": "Change detected (Δ +407 chars)"
    },
    {
      "date": "2026-06-18T11:52:30.360Z",
      "region": "Robotics & Machinery Safety",
      "authority": "OSHA",
      "url": "https://www.osha.gov/robotics",
      "note": "Change detected (Δ -349 chars)"
    },
    {
      "date": "2026-06-18T11:52:33.346Z",
      "region": "Functional Safety",
      "authority": "ISO/TC 22",
      "url": "https://www.iso.org/committee/46706.html",
      "note": "Change detected (Δ -46 chars)"
    },
    {
      "date": "2026-06-18T11:52:34.802Z",
      "region": "Functional Safety",
      "authority": "IEC",
      "url": "https://www.iec.ch/functionalsafety",
      "note": "Change detected (Δ -197 chars)"
    },
    {
      "date": "2026-06-18T11:52:41.084Z",
      "region": "AI Governance",
      "authority": "European Commission",
      "url": "https://digital-strategy.ec.europa.eu/en/policies/regulatory-framework-ai",
      "note": "Change detected (Δ -18211 chars)"
    }
  ]
}
